disklru/__init__.py
disklru/disklru.py
disklru-2.0.4.dist-info/LICENSE
disklru-2.0.4.dist-info/METADATA
disklru-2.0.4.dist-info/WHEEL
disklru-2.0.4.dist-info/top_level.txt
disklru-2.0.4.dist-info/RECORD
