Metadata-Version: 2.1
Name: disklru
Version: 2.0.4
Home-page: https://github.com/zackees/disklru
Maintainer: Zachary Vorhies
Requires-Python: >=3.8
License-File: LICENSE
Provides-Extra: dev
Requires-Dist: black; extra == "dev"
Requires-Dist: isort; extra == "dev"
Requires-Dist: flake8; extra == "dev"
Requires-Dist: mypy; extra == "dev"
Requires-Dist: pylint; extra == "dev"
Requires-Dist: pytest; extra == "dev"
Requires-Dist: tox; extra == "dev"
Requires-Dist: ruff; extra == "dev"
